diffcool.py
diffcool-0.1.1.dist-info/METADATA
diffcool-0.1.1.dist-info/WHEEL
diffcool-0.1.1.dist-info/entry_points.txt
diffcool-0.1.1.dist-info/licenses/LICENSE
diffcool-0.1.1.dist-info/RECORD
